service.py
iflow_mcp_frosty_jackal_mcpdemo-0.1.0.dist-info/METADATA
iflow_mcp_frosty_jackal_mcpdemo-0.1.0.dist-info/WHEEL
iflow_mcp_frosty_jackal_mcpdemo-0.1.0.dist-info/entry_points.txt
iflow_mcp_frosty_jackal_mcpdemo-0.1.0.dist-info/RECORD
