Metadata-Version: 2.4
Name: iflow-mcp_frosty-jackal-mcpdemo
Version: 0.1.0
Summary: MCP Demo - OCR service using PaddleOCR
Requires-Python: >=3.10
Requires-Dist: mcp>=1.18.0
Requires-Dist: numpy>=2.2.6
Requires-Dist: paddleocr>=3.3.0
Requires-Dist: paddlepaddle>=3.2.0
Requires-Dist: pillow>=11.3.0
